avahiplatform/__init__.py
avahiplatform/platform_core.py
avahiplatform/helpers/__init__.py
avahiplatform/helpers/chats/__init__.py
avahiplatform/helpers/chats/anthropic_chat.py
avahiplatform/helpers/chats/base_chat.py
avahiplatform/helpers/chats/bedrock_chat.py
avahiplatform/helpers/connectors/__init__.py
avahiplatform/helpers/connectors/boto_helper.py
avahiplatform/helpers/connectors/s3_helper.py
avahiplatform/helpers/connectors/utils.py
avahiplatform/helpers/embedding_helper/__init__.py
avahiplatform/helpers/embedding_helper/base_embeddings.py
avahiplatform/helpers/embedding_helper/bedrock_embeddings.py
avahiplatform/helpers/image_helper/__init__.py
avahiplatform/helpers/image_helper/base_image_generation.py
avahiplatform/helpers/image_helper/bedrock_image_generation.py
avahiplatform/src/Observability.py
avahiplatform/src/__init__.py
avahiplatform/src/chatbot.py
avahiplatform/src/create_ui_wrapper_from_gradio.py
avahiplatform/src/data_masking.py
avahiplatform/src/grammarCorrection.py
avahiplatform/src/icd_code_generator.py
avahiplatform/src/imageGeneration.py
avahiplatform/src/imageSimilarity.py
avahiplatform/src/medical_scribing.py
avahiplatform/src/nl2sql.py
avahiplatform/src/productDescriptionGeneration.py
avahiplatform/src/query_csv.py
avahiplatform/src/rag_semantic_search.py
avahiplatform/src/structredExtraction.py
avahiplatform/src/summarizer.py
avahiplatform-0.0.21.dist-info/LICENSE
avahiplatform-0.0.21.dist-info/METADATA
avahiplatform-0.0.21.dist-info/WHEEL
avahiplatform-0.0.21.dist-info/top_level.txt
avahiplatform-0.0.21.dist-info/RECORD
