Metadata-Version: 2.2
Name: avahiplatform
Version: 0.0.21
Summary: An avahiai library which makes your Gen-AI tasks effortless
Home-page: https://github.com/avahi-org/avahiplatform
Author: Avahi AWS
Author-email: info@avahitech.com
License: MIT
Classifier: License :: OSI Approved :: MIT License
Classifier: Programming Language :: Python :: 3.9
Classifier: Operating System :: OS Independent
Requires-Python: >=3.9
License-File: LICENSE
Requires-Dist: boto3>=1.34.160
Requires-Dist: loguru>=0.7.2
Requires-Dist: python-docx>=1.1.2
Requires-Dist: PyMuPDF>=1.24.9
Requires-Dist: psycopg2>=2.9.9
Requires-Dist: PyMySQL>=1.1.1
Requires-Dist: tabulate>=0.9.0
Requires-Dist: pillow>=10.4.0
Requires-Dist: sqlalchemy>=2.0.35
Requires-Dist: pandas>=2.2.3
Requires-Dist: gradio>=4.44.0
Requires-Dist: typing_extensions>=4.0.0
Requires-Dist: prometheus-client>=0.21.0
Requires-Dist: python-magic>=0.4.27
Requires-Dist: anthropic>=0.42.0
Provides-Extra: dev
Requires-Dist: twine>=4.0.2; extra == "dev"
Dynamic: author
Dynamic: author-email
Dynamic: classifier
Dynamic: description
Dynamic: description-content-type
Dynamic: home-page
Dynamic: license
Dynamic: provides-extra
Dynamic: requires-dist
Dynamic: requires-python
Dynamic: summary
